fc_dxp_lds.py
fc_dxp_lds-1.0.dist-info/METADATA
fc_dxp_lds-1.0.dist-info/WHEEL
fc_dxp_lds-1.0.dist-info/top_level.txt
fc_dxp_lds-1.0.dist-info/RECORD
