Metadata-Version: 2.1
Name: fc-dxp-lds
Version: 1.0
Summary: 刘大帅
Home-page: UNKNOWN
Author: 刘大帅
Author-email: fc@bigdate.com
License: UNKNOWN
Platform: UNKNOWN
